nunja-0.1.0-py3.6-nspkg.pth
nunja/__core__.js
nunja/core.js
nunja/core.py
nunja/engine.js
nunja/engine.py
nunja/exc.py
nunja/index.js
nunja/indexer.py
nunja/loader.js
nunja/loader.py
nunja/registry.js
nunja/registry.py
nunja/spec.py
nunja/utils.js
nunja/_core_/_default_wrapper_/template.nja
nunja/molds/README.rst
nunja/molds/html5/template.nja
nunja/molds/navtable/template.nja
nunja/molds/table/template.nja
nunja/templates/builtin/html5.nja
nunja/testing/__init__.py
nunja/testing/mocks.py
nunja/testing/model.py
nunja/testing/badmold/file
nunja/testing/badmold/nomold/README.txt
nunja/testing/badmold/nomold/empty.nja
nunja/testing/mold/basic/template.nja
nunja/testing/mold/include_by_name/empty.nja
nunja/testing/mold/include_by_name/index.js
nunja/testing/mold/include_by_name/template.nja
nunja/testing/mold/include_by_value/index.js
nunja/testing/mold/include_by_value/template.nja
nunja/testing/mold/itemlist/index.js
nunja/testing/mold/itemlist/template.nja
nunja/testing/mold/noinit/index.js
nunja/testing/mold/noinit/template.nja
nunja/testing/mold/problem/index.js
nunja/testing/mold/problem/template.nja
nunja/tests/__init__.py
nunja/tests/test_core.js
nunja/tests/test_core.py
nunja/tests/test_engine.js
nunja/tests/test_engine.py
nunja/tests/test_indexer.py
nunja/tests/test_loader.py
nunja/tests/test_mold_navtable.js
nunja/tests/test_mold_navtable.py
nunja/tests/test_mold_table.js
nunja/tests/test_mold_table.py
nunja/tests/test_registry.js
nunja/tests/test_registry.py
nunja/tests/test_render.py
nunja/tests/test_spec.py
nunja/tests/test_testing_mocks.py
nunja/tests/test_testing_model.py
nunja/tests/test_utils.js
nunja/tests/rjs/README.rst
nunja/tests/rjs/__init__.py
nunja/tests/rjs/test_engine.js
nunja/tests/rjs/test_index.js
nunja/tests/rjs/test_loader.js
nunja-0.1.0.dist-info/calmjs_artifacts/nunja.js
nunja-0.1.0.dist-info/LICENSE
nunja-0.1.0.dist-info/METADATA
nunja-0.1.0.dist-info/WHEEL
nunja-0.1.0.dist-info/calmjs_artifacts.json
nunja-0.1.0.dist-info/calmjs_module_registry.txt
nunja-0.1.0.dist-info/entry_points.txt
nunja-0.1.0.dist-info/extras_calmjs.json
nunja-0.1.0.dist-info/namespace_packages.txt
nunja-0.1.0.dist-info/package.json
nunja-0.1.0.dist-info/top_level.txt
nunja-0.1.0.dist-info/RECORD
