Metadata-Version: 2.1
Name: nunja
Version: 0.1.0
Summary: The unified templating framework for Python x JavaScript
Home-page: https://github.com/calmjs/nunja
Author: Tommy Yu
Author-email: tommy.yu@auckland.ac.nz
License: GPL
Platform: UNKNOWN
Classifier: Development Status :: 4 - Beta
Classifier: Environment :: Console
Classifier: Intended Audience :: Developers
Classifier: License :: OSI Approved :: GNU General Public License v2 or later (GPLv2+)
Classifier: Operating System :: OS Independent
Classifier: Programming Language :: JavaScript
Classifier: Programming Language :: Python :: 2.7
Classifier: Programming Language :: Python :: 3.3
Classifier: Programming Language :: Python :: 3.4
Classifier: Programming Language :: Python :: 3.5
Classifier: Programming Language :: Python :: 3.6
Requires-Python: >=2.7,!=3.0.*,!=3.1.*,!=3.2.*
Requires-Dist: Jinja2 (>=2.4)
Requires-Dist: calmjs (>=3.4.1)
Provides-Extra: dev
Requires-Dist: calmjs.dev (>=2.3.0) ; extra == 'dev'
Provides-Extra: rjs
Requires-Dist: calmjs.rjs ; extra == 'rjs'
Provides-Extra: webpack
Requires-Dist: calmjs.webpack ; extra == 'webpack'
